pylint_venv.py
pylint_venv-3.0.2.dist-info/LICENSE.txt
pylint_venv-3.0.2.dist-info/METADATA
pylint_venv-3.0.2.dist-info/WHEEL
pylint_venv-3.0.2.dist-info/RECORD
