Metadata-Version: 2.1
Name: pylint-venv
Version: 3.0.2
Summary: pylint-venv provides a Pylint init-hook to use the same Pylint installation with different virtual environments.
Home-page: https://github.com/jgosmann/pylint-venv/
License: MIT
Keywords: pylint,virtualenv,venv
Author: Jan Gosmann
Author-email: jan@hyper-world.de
Maintainer: Jan Gosmann
Maintainer-email: jan@hyper-world.de
Requires-Python: >=3.7.2,<4.0.0
Classifier: Development Status :: 5 - Production/Stable
Classifier: Environment :: Plugins
Classifier: Intended Audience :: Developers
Classifier: License :: OSI Approved :: MIT License
Classifier: Programming Language :: Python
Classifier: Programming Language :: Python :: 3
Classifier: Programming Language :: Python :: 3.8
Classifier: Programming Language :: Python :: 3.9
Classifier: Programming Language :: Python :: 3.10
Classifier: Programming Language :: Python :: 3.11
Classifier: Programming Language :: Python :: 3.7
Classifier: Programming Language :: Python :: Implementation :: CPython
Classifier: Programming Language :: Python :: Implementation :: PyPy
Classifier: Topic :: Software Development
Project-URL: Repository, https://github.com/jgosmann/pylint-venv/
